RV32I/RTL/ProgramCounter/pc_unit.v
`timescale 1ns/1ps


module pc_unit(
    input  wire        clk,
    input  wire        reset,
    input  wire        stall,			//pc_src = 0  →  Next PC = PC + 4      (normal, go to next instruction)
                                                //pc_src = 1  →  Next PC = branch_target (jump to new address)
    input  wire        pc_src,			
    input  wire [31:0] branch_target,		// next instruction address
    output reg  [31:0] pc,			// present address
    output wire [31:0] pc_plus_4 		// just pc + 4
);
    assign pc_plus_4 = pc + 4;
    
    always @(posedge clk or posedge reset) begin
    	if(reset) begin
    		pc <= 32'h00000000;
    	end
    	
    	else if (stall) begin
    		pc <= pc;
    	end
    	
    	else if (pc_src) begin
    		pc <= branch_target;   	
    	end
    	
    	else begin
    		pc <= pc_plus_4;
    	
    	end
    end

endmodule

/*
                    ┌─────────────────────────────────────┐
                    │            PC UNIT                  │
                    │                                     │
    reset ─────────►│  ┌───────────┐                      │
                    │  │           │                      │
    clk ───────────►│  │    PC     │────────────────────► ├──── pc[31:0]
                    │  │  Register │                      │
    stall ─────────►│  │           │      ┌─────────┐     │
                    │  └─────┬─────┘      │  Adder  │     │
                    │        │            │  (+4)   │───► ├──── pc_plus_4[31:0]
                    │        │            └────┬────┘     │
                    │        │                 │          │
                    │        ▼                 │          │
                    │     ┌─────┐              │          │
    pc_src ────────►│     │ MUX │◄─────────────┘          │
                    │     └──┬──┘                         │
                    │        ▲                            │
    branch_target ─►│        │                            │
                    │        │                            │
                    └────────┴────────────────────────────┘

*/

RV32I/RTL/ProgramCounter/tb_pc_unit.v
`timescale 1ns/1ps

module tb_pc_unit;

    // Inputs
    reg        clk;
    reg        reset;
    reg        stall;
    reg        pc_src;
    reg [31:0] branch_target;
    
    // Outputs
    wire [31:0] pc;
    wire [31:0] pc_plus_4;
    
    // Instantiate PC Unit
    pc_unit uut (
        .clk(clk),
        .reset(reset),
        .stall(stall),
        .pc_src(pc_src),
        .branch_target(branch_target),
        .pc(pc),
        .pc_plus_4(pc_plus_4)
    );
    
    // Clock generation: 10ns period
    always #5 clk = ~clk;
    
    // Test sequence
    initial begin
        // Setup waveform dump
        $dumpfile("pc_unit_wave.vcd");
        $dumpvars(0, tb_pc_unit);
        
        // Initialize
        clk = 0;
        reset = 0;
        stall = 0;
        pc_src = 0;
        branch_target = 32'h0;
        
        // ========== TEST 1: Reset ==========
        $display("\n=== TEST 1: Reset ===");
        reset = 1;
        #10;
        reset = 0;
        
        if (pc == 32'h0)
            $display("PASS: PC = 0x%08h after reset", pc);
        else
            $display("FAIL: PC = 0x%08h, expected 0x00000000", pc);
        
        // ========== TEST 2: Normal Increment ==========
        $display("\n=== TEST 2: Normal Increment ===");
        
        #10; // One clock cycle
        if (pc == 32'h4)
            $display("PASS: PC = 0x%08h (incremented to 4)", pc);
        else
            $display("FAIL: PC = 0x%08h, expected 0x00000004", pc);
            
        #10; // Another clock cycle
        if (pc == 32'h8)
            $display("PASS: PC = 0x%08h (incremented to 8)", pc);
        else
            $display("FAIL: PC = 0x%08h, expected 0x00000008", pc);
            
        #10; // Another clock cycle
        if (pc == 32'hC)
            $display("PASS: PC = 0x%08h (incremented to C)", pc);
        else
            $display("FAIL: PC = 0x%08h, expected 0x0000000C", pc);
        
        // ========== TEST 3: Stall ==========
        $display("\n=== TEST 3: Stall ===");
        stall = 1;
        #10;
        
        if (pc == 32'hC)
            $display("PASS: PC = 0x%08h (held during stall)", pc);
        else
            $display("FAIL: PC = 0x%08h, expected 0x0000000C", pc);
        
        #10; // Still stalled
        if (pc == 32'hC)
            $display("PASS: PC = 0x%08h (still held)", pc);
        else
            $display("FAIL: PC = 0x%08h, expected 0x0000000C", pc);
        
        stall = 0;
        
        // ========== TEST 4: Branch ==========
        $display("\n=== TEST 4: Branch ===");
        #10; // PC should increment first
        
        pc_src = 1;
        branch_target = 32'h00000100;
        #10;
        
        if (pc == 32'h100)
            $display("PASS: PC = 0x%08h (branched to target)", pc);
        else
            $display("FAIL: PC = 0x%08h, expected 0x00000100", pc);
        
        pc_src = 0;
        
        // ========== TEST 5: Continue after branch ==========
        $display("\n=== TEST 5: Continue after branch ===");
        #10;
        
        if (pc == 32'h104)
            $display("PASS: PC = 0x%08h (incremented from branch target)", pc);
        else
            $display("FAIL: PC = 0x%08h, expected 0x00000104", pc);
        
        // ========== TEST 6: PC + 4 Output ==========
        $display("\n=== TEST 6: PC + 4 Output ===");
        
        if (pc_plus_4 == pc + 4)
            $display("PASS: pc_plus_4 = 0x%08h (correct)", pc_plus_4);
        else
            $display("FAIL: pc_plus_4 = 0x%08h, expected 0x%08h", pc_plus_4, pc + 4);
        
        // ========== SUMMARY ==========
        $display("\n=== ALL TESTS COMPLETE ===\n");
        
        #20;
        $finish;
    end
    
    // Monitor PC changes
    always @(posedge clk) begin
        $display("Time=%0t: PC=0x%08h, PC+4=0x%08h, stall=%b, pc_src=%b", 
                 $time, pc, pc_plus_4, stall, pc_src);
    end

endmodule

RV32I/RTL/ProgramCounter/pc_unit_wave.vcd
$date
	Sun Nov 23 04:57:53 2025
$end
$version
	Icarus Verilog
$end
$timescale
	1ps
$end
$scope module tb_pc_unit $end
$var wire 32 ! pc_plus_4 [31:0] $end
$var wire 32 " pc [31:0] $end
$var reg 32 # branch_target [31:0] $end
$var reg 1 $ clk $end
$var reg 1 % pc_src $end
$var reg 1 & reset $end
$var reg 1 ' stall $end
$scope module uut $end
$var wire 32 ( branch_target [31:0] $end
$var wire 1 $ clk $end
$var wire 1 % pc_src $end
$var wire 1 & reset $end
$var wire 1 ' stall $end
$var wire 32 ) pc_plus_4 [31:0] $end
$var reg 32 * pc [31:0] $end
$upscope $end
$upscope $end
$enddefinitions $end
$comment Show the parameter values. $end
$dumpall
$end
#0
$dumpvars
b0 *
b100 )
b0 (
0'
1&
0%
0$
b0 #
b0 "
b100 !
$end
#5000
1$
#10000
0$
0&
#15000
b1000 !
b1000 )
b100 "
b100 *
1$
#20000
0$
#25000
b1100 !
b1100 )
b1000 "
b1000 *
1$
#30000
0$
#35000
b10000 !
b10000 )
b1100 "
b1100 *
1$
#40000
0$
1'
#45000
1$
#50000
0$
#55000
1$
#60000
0$
0'
#65000
b10100 !
b10100 )
b10000 "
b10000 *
1$
#70000
0$
b100000000 #
b100000000 (
1%
#75000
b100000100 !
b100000100 )
b100000000 "
b100000000 *
1$
#80000
0$
0%
#85000
b100001000 !
b100001000 )
b100000100 "
b100000100 *
1$
#90000
0$
#95000
b100001100 !
b100001100 )
b100001000 "
b100001000 *
1$
#100000
0$
#105000
b100010000 !
b100010000 )
b100001100 "
b100001100 *
1$
